un_yaml/__init__.py
un_yaml/cli.yaml
un_yaml/py.typed
un_yaml/un_cli.py
un_yaml/un_conf.py
un_yaml/un_uri.py
un_yaml/un_yaml.py
un_yaml/wrapper.py
un_yaml-0.3.1.dist-info/LICENSE
un_yaml-0.3.1.dist-info/METADATA
un_yaml-0.3.1.dist-info/WHEEL
un_yaml-0.3.1.dist-info/RECORD
