Metadata-Version: 2.1
Name: un-yaml
Version: 0.3.1
Summary: Universal YAML: replace repetitive code with your own Domain-Specific un-Language (DSuL)
Author: Ernest Prabhakar
Author-email: ernest@quiltdata.io
Requires-Python: >=3.10,<4.0
Classifier: Programming Language :: Python :: 3
Classifier: Programming Language :: Python :: 3.10
Classifier: Programming Language :: Python :: 3.11
Requires-Dist: anyio (>=3.7.0,<4.0.0)
Requires-Dist: asyncclick (>=8.1.3.4,<9.0.0.0)
Requires-Dist: pyyaml (>=6.0,<7.0)
Requires-Dist: trio (>=0.22.0,<0.23.0)
Requires-Dist: types-pyyaml (>=6.0.12.10,<7.0.0.0)
Requires-Dist: typing-extensions (>=4.5.0,<5.0.0)
